card_deck_wiessall/__init__.py
card_deck_wiessall/_nbdev.py
card_deck_wiessall/card.py
card_deck_wiessall-0.0.1.dist-info/LICENSE
card_deck_wiessall-0.0.1.dist-info/METADATA
card_deck_wiessall-0.0.1.dist-info/WHEEL
card_deck_wiessall-0.0.1.dist-info/entry_points.txt
card_deck_wiessall-0.0.1.dist-info/top_level.txt
card_deck_wiessall-0.0.1.dist-info/RECORD
