Metadata-Version: 2.1
Name: card-deck-wiessall
Version: 0.0.1
Summary: "Minimal example of nbdev"
Home-page: https://github.com/wiessall/card_deck_wiessall/tree/{branch}/
Author: Tristan Wiessalla
Author-email: tristan.wiessalla@embl.it
License: Apache Software License 2.0
Keywords: "nbdev tutorial"
Platform: UNKNOWN
Classifier: Development Status :: 3 - Alpha
Classifier: Intended Audience :: Developers
Classifier: Natural Language :: English
Classifier: Programming Language :: Python :: 3.6
Classifier: Programming Language :: Python :: 3.7
Classifier: Programming Language :: Python :: 3.8
Classifier: License :: OSI Approved :: Apache Software License
Requires-Python: >=3.6
License-File: LICENSE
Requires-Dist: pip
Requires-Dist: packaging
Provides-Extra: dev
